AUTHORS.rst
CONTRIBUTING.rst
HISTORY.rst
LICENSE
MANIFEST.in
README.rst
setup.cfg
setup.py
docs/Makefile
docs/authors.rst
docs/conf.py
docs/contributing.rst
docs/history.rst
docs/index.rst
docs/installation.rst
docs/make.bat
docs/readme.rst
docs/usage.rst
pydiggy/__init__.py
pydiggy/__main__.py
pydiggy/cli.py
pydiggy/connection.py
pydiggy/exceptions.py
pydiggy/node.py
pydiggy/operations.py
pydiggy/types.py
pydiggy/utils.py
pydiggy.egg-info/PKG-INFO
pydiggy.egg-info/SOURCES.txt
pydiggy.egg-info/dependency_links.txt
pydiggy.egg-info/entry_points.txt
pydiggy.egg-info/not-zip-safe
pydiggy.egg-info/requires.txt
pydiggy.egg-info/top_level.txt
tests/__init__.py
tests/conftest.py
tests/test_hydration.py
tests/test_missing.py
tests/test_mutation.py
tests/test_node.py
tests/test_operations.py
tests/test_pydiggy.py
tests/test_reverse.py
tests/fakeapp/__init__.py
tests/fakeapp/basic.py